ansys/grantami/recordlists/__init__.py
ansys/grantami/recordlists/_connection.py
ansys/grantami/recordlists/_logger.py
ansys/grantami/recordlists/_models.py
ansys/grantami/recordlists/py.typed
ansys_grantami_recordlists-2.0.1.dist-info/AUTHORS
ansys_grantami_recordlists-2.0.1.dist-info/LICENSE
ansys_grantami_recordlists-2.0.1.dist-info/METADATA
ansys_grantami_recordlists-2.0.1.dist-info/WHEEL
ansys_grantami_recordlists-2.0.1.dist-info/RECORD
