Metadata-Version: 2.3
Name: ansys-grantami-recordlists
Version: 2.0.1
Summary: A python wrapper for the Granta MI RecordLists API
License: MIT
Author: ANSYS, Inc.
Author-email: pyansys.core@ansys.com
Maintainer: ANSYS, Inc.
Maintainer-email: pyansys.core@ansys.com
Requires-Python: >=3.10,<4.0
Classifier: Development Status :: 4 - Beta
Classifier: License :: OSI Approved :: MIT License
Classifier: Operating System :: OS Independent
Classifier: Programming Language :: Python :: 3
Classifier: Programming Language :: Python :: 3.10
Classifier: Programming Language :: Python :: 3.11
Classifier: Programming Language :: Python :: 3.12
Classifier: Programming Language :: Python :: 3.13
Requires-Dist: ansys-grantami-serverapi-openapi (>=5.0,<6.0)
Requires-Dist: ansys-openapi-common (>=2.0.0,<3.0.0)
Requires-Dist: requests (>=2.26,<3.0)
Project-URL: Documentation, https://recordlists.grantami.docs.pyansys.com
Project-URL: Repository, https://github.com/ansys/grantami-recordlists
